setup.py
sarf_postgres_tools/__init__.py
sarf_postgres_tools/sarf_postgres_tools.py
sarf_postgres_tools.egg-info/PKG-INFO
sarf_postgres_tools.egg-info/SOURCES.txt
sarf_postgres_tools.egg-info/dependency_links.txt
sarf_postgres_tools.egg-info/entry_points.txt
sarf_postgres_tools.egg-info/requires.txt
sarf_postgres_tools.egg-info/top_level.txt