Metadata-Version: 2.1
Name: sarf-postgres-tools
Version: 0.1.0
Summary: This module allows you to save SARF tools messages into postgresql
Home-page: https://github.com/elchicodepython/SARF-Security-Assesment-and-Reporting-Framework
Author: Samuel López Saura
Author-email: samuellopezsaura@gmail.com
License: MIT
Platform: UNKNOWN
Classifier: Programming Language :: Python :: 3
Classifier: License :: OSI Approved :: MIT License
Classifier: Operating System :: OS Independent
